{
    "provider": "Gold API",
    "generated": "2026-07-17T08:57:58.774Z",
    "updated": "2026-07-17T08:57:49Z",
    "currencies": {
        "USD": {
            "symbol": "$",
            "gold": {
                "24K": 128.55,
                "22K": 117.84,
                "21K": 112.48,
                "19.2K": 102.84,
                "18K Yellow": 96.41,
                "18K White": 96.41,
                "14K": 74.99,
                "10K": 53.56,
                "9K": 48.21
            },
            "silver": {
                "925": 1.66,
                "999": 1.79
            },
            "platinum": {
                "950": 48.62,
                "999": 51.18
            },
            "palladium": {
                "950": 38.55,
                "999": 40.57
            }
        },
        "EUR": {
            "symbol": "€",
            "gold": {
                "24K": 112.29,
                "22K": 102.93,
                "21K": 98.25,
                "19.2K": 89.83,
                "18K Yellow": 84.22,
                "18K White": 84.22,
                "14K": 65.5,
                "10K": 46.79,
                "9K": 42.11
            },
            "silver": {
                "925": 1.45,
                "999": 1.56
            },
            "platinum": {
                "950": 42.47,
                "999": 44.71
            },
            "palladium": {
                "950": 33.67,
                "999": 35.44
            }
        },
        "GBP": {
            "symbol": "£",
            "gold": {
                "24K": 95.32,
                "22K": 87.38,
                "21K": 83.4,
                "19.2K": 76.25,
                "18K Yellow": 71.49,
                "18K White": 71.49,
                "14K": 55.6,
                "10K": 39.72,
                "9K": 35.74
            },
            "silver": {
                "925": 1.23,
                "999": 1.33
            },
            "platinum": {
                "950": 36.06,
                "999": 37.95
            },
            "palladium": {
                "950": 28.58,
                "999": 30.09
            }
        },
        "CHF": {
            "symbol": "CHF",
            "gold": {
                "24K": 103.91,
                "22K": 95.25,
                "21K": 90.92,
                "19.2K": 83.12,
                "18K Yellow": 77.93,
                "18K White": 77.93,
                "14K": 60.61,
                "10K": 43.29,
                "9K": 38.96
            },
            "silver": {
                "925": 1.34,
                "999": 1.45
            },
            "platinum": {
                "950": 39.3,
                "999": 41.37
            },
            "palladium": {
                "950": 31.16,
                "999": 32.8
            }
        },
        "JPY": {
            "symbol": "¥",
            "gold": {
                "24K": 20867.35,
                "22K": 19128.41,
                "21K": 18258.93,
                "19.2K": 16693.88,
                "18K Yellow": 15650.52,
                "18K White": 15650.52,
                "14K": 12172.62,
                "10K": 8694.73,
                "9K": 7825.26
            },
            "silver": {
                "925": 268.71,
                "999": 290.5
            },
            "platinum": {
                "950": 7893.3,
                "999": 8308.74
            },
            "palladium": {
                "950": 6257.13,
                "999": 6586.45
            }
        },
        "CNY": {
            "symbol": "¥",
            "gold": {
                "24K": 871.6,
                "22K": 798.96,
                "21K": 762.65,
                "19.2K": 697.28,
                "18K Yellow": 653.7,
                "18K White": 653.7,
                "14K": 508.43,
                "10K": 363.17,
                "9K": 326.85
            },
            "silver": {
                "925": 11.22,
                "999": 12.13
            },
            "platinum": {
                "950": 329.69,
                "999": 347.04
            },
            "palladium": {
                "950": 261.35,
                "999": 275.11
            }
        },
        "HKD": {
            "symbol": "HK$",
            "gold": {
                "24K": 1007.75,
                "22K": 923.78,
                "21K": 881.79,
                "19.2K": 806.2,
                "18K Yellow": 755.82,
                "18K White": 755.82,
                "14K": 587.86,
                "10K": 419.9,
                "9K": 377.91
            },
            "silver": {
                "925": 12.98,
                "999": 14.03
            },
            "platinum": {
                "950": 381.19,
                "999": 401.26
            },
            "palladium": {
                "950": 302.18,
                "999": 318.08
            }
        },
        "SGD": {
            "symbol": "S$",
            "gold": {
                "24K": 165.83,
                "22K": 152.01,
                "21K": 145.1,
                "19.2K": 132.66,
                "18K Yellow": 124.37,
                "18K White": 124.37,
                "14K": 96.73,
                "10K": 69.09,
                "9K": 62.19
            },
            "silver": {
                "925": 2.14,
                "999": 2.31
            },
            "platinum": {
                "950": 62.73,
                "999": 66.03
            },
            "palladium": {
                "950": 49.72,
                "999": 52.34
            }
        },
        "AUD": {
            "symbol": "A$",
            "gold": {
                "24K": 183.66,
                "22K": 168.35,
                "21K": 160.7,
                "19.2K": 146.93,
                "18K Yellow": 137.74,
                "18K White": 137.74,
                "14K": 107.13,
                "10K": 76.52,
                "9K": 68.87
            },
            "silver": {
                "925": 2.36,
                "999": 2.56
            },
            "platinum": {
                "950": 69.47,
                "999": 73.13
            },
            "palladium": {
                "950": 55.07,
                "999": 57.97
            }
        },
        "CAD": {
            "symbol": "C$",
            "gold": {
                "24K": 180.44,
                "22K": 165.41,
                "21K": 157.89,
                "19.2K": 144.35,
                "18K Yellow": 135.33,
                "18K White": 135.33,
                "14K": 105.26,
                "10K": 75.18,
                "9K": 67.67
            },
            "silver": {
                "925": 2.32,
                "999": 2.51
            },
            "platinum": {
                "950": 68.25,
                "999": 71.85
            },
            "palladium": {
                "950": 54.11,
                "999": 56.95
            }
        }
    }
}